scilab2py/__init__.py
scilab2py/compat.py
scilab2py/core.py
scilab2py/demo.py
scilab2py/matread.py
scilab2py/matwrite.py
scilab2py/speed_check.py
scilab2py/thread_check.py
scilab2py/utils.py
scilab2py/ipython/__init__.py
scilab2py/ipython/scilabmagic.py
scilab2py/ipython/tests/__init__.py
scilab2py/ipython/tests/test_scilabmagic.py
scilab2py/tests/__init__.py
scilab2py/tests/roundtrip.sci
scilab2py/tests/test_conversions.py
scilab2py/tests/test_datatypes.sci
scilab2py/tests/test_misc.py
scilab2py/tests/test_nodocstring.sci
scilab2py/tests/test_numpy.py
scilab2py/tests/test_roundtrip.py
scilab2py/tests/test_usage.py
scilab2py-0.6.2.dist-info/METADATA
scilab2py-0.6.2.dist-info/RECORD
scilab2py-0.6.2.dist-info/WHEEL
scilab2py-0.6.2.dist-info/top_level.txt
