Metadata-Version: 1.2
Name: scilab2py
Version: 0.6.2
Summary: Python to Scilab bridge
Home-page: http://github.com/blink1073/scilab2py
Maintainer: Steven Silvester
Maintainer-email: steven.silvester@ieee.org
License: MIT
Download-URL: http://github.com/blink1073/scilab2py
Platform: Any
Classifier: Development Status :: 4 - Beta
Classifier: Intended Audience :: Developers
Classifier: Intended Audience :: Science/Research
Classifier: License :: OSI Approved :: MIT License
Classifier: Operating System :: OS Independent
Classifier: Programming Language :: Python
Classifier: Programming Language :: Python :: 2.7
Classifier: Programming Language :: Python :: 3.3
Classifier: Programming Language :: Python :: 3.4
Classifier: Topic :: Scientific/Engineering
Classifier: Topic :: Software Development
Requires: numpy (>= 1.7.1)
Requires: scipy (>= 0.12)
